LICENSE
MANIFEST.in
README.md
setup.py
youtube_sentiment/__init__.py
youtube_sentiment/logger.py
youtube_sentiment/main.py
youtube_sentiment/nlp.py
youtube_sentiment/service.py
youtube_sentiment/utility.py
youtube_sentiment/youtube.py
youtube_sentiment.egg-info/PKG-INFO
youtube_sentiment.egg-info/SOURCES.txt
youtube_sentiment.egg-info/dependency_links.txt
youtube_sentiment.egg-info/not-zip-safe
youtube_sentiment.egg-info/requires.txt
youtube_sentiment.egg-info/top_level.txt
youtube_sentiment/models/lr_sentiment_basic.pkl
youtube_sentiment/models/lr_sentiment_cv.pkl