Metadata-Version: 2.1
Name: youtube-sentiment
Version: 0.3.0
Summary: Analyze Youtube videos for general sentiment analysis
Home-page: https://github.com/dillonmabry/youtube-sentiment-helper
Author: Dillon Mabry
Author-email: rapid.dev.solutions@gmail.com
License: MIT
Platform: UNKNOWN
